wikibrain/__init__.py
wikibrain/apply_changes.py
wikibrain/wikidata_knowledge.py
wikibrain/wikimedia_link_issue_reporter.py
wikibrain/wikipedia_knowledge.py
wikibrain-0.0.7.dist-info/LICENSE
wikibrain-0.0.7.dist-info/METADATA
wikibrain-0.0.7.dist-info/WHEEL
wikibrain-0.0.7.dist-info/top_level.txt
wikibrain-0.0.7.dist-info/RECORD
